{
  "basics": {
    "name": "Santiago Arróniz",
    "label": "Linguist",
    "image": "",
    "email": "sarroniz@indiana.edu",
    "url": "https://www.sarroniz.com",
    "summary": "Phonologist and Computational Linguist",
    "location": {
      "address": "355 N Jordan Ave GISB 2115",
      "postalCode": "IN 47405",
      "city": "Bloomington",
      "countryCode": "US",
      "region": "Indiana"
    },
    "profiles": [
      {
        "network": "Twitter",
        "username": "ArronizSantiago",
        "url": "https://twitter.com/ArronizSantiago"
      }
    ]
  },
  "work": [
    {
      "name": "Department of Spanish and Portuguese, Indiana University",
      "position": "Associate Instructor",
      "url": "https://spanport.indiana.edu",
      "startDate": "2016",
      "endDate": "2023",
      "summary": "Teaching different undergraduate courses at Indiana University while getting my Ph.D.",
    }
  ],
  "volunteer": [],
  "education": [
    {
      "institution": "Indiana University, Bloomington, US",
      "url": "https://www.iu.edu/",
      "area": "Hispanic / Computational Linguistics",
      "studyType": "Ph.D.",
      "startDate": "2019",
      "endDate": "Present",
      "score": "",
    },
  ],
  "awards": [
    {
      "title": "Nobel Prize in Physics",
      "date": "1921-11-01",
      "awarder": "Royal Swedish Academy of Sciences",
      "summary": "The Nobel Prizes are five separate prizes that, according to Alfred Nobel's will of 1895, are awarded to 'those who, during the preceding year, have conferred the greatest benefit to humankind.'"
    }
  ],
  "certificates": [],
  "publications": [],
  "skills": [],
  "languages": [
    {
      "language": "German",
      "fluency": "Native speaker"
    },
    {
      "language": "English",
      "fluency": "Fluent"
    }
  ],
  "interests": [],
  "references": [],
  "projects": []
}